README.txt
dev.cfg
fellowiki.py
sample-prod.cfg
setup.cfg
setup.py
FelloWiki.egg-info/PKG-INFO
FelloWiki.egg-info/SOURCES.txt
FelloWiki.egg-info/dependency_links.txt
FelloWiki.egg-info/not-zip-safe
FelloWiki.egg-info/requires.txt
FelloWiki.egg-info/top_level.txt
fellowiki/__init__.py
fellowiki/json.py
fellowiki/config/__init__.py
fellowiki/config/app.cfg
fellowiki/config/log.cfg
fellowiki/controllers/__init__.py
fellowiki/controllers/wiki.py
fellowiki/controllers/wikiparser/__init__.py
fellowiki/controllers/wikiparser/escaped_text.py
fellowiki/controllers/wikiparser/headlines.py
fellowiki/controllers/wikiparser/links.py
fellowiki/controllers/wikiparser/lists.py
fellowiki/controllers/wikiparser/macros.py
fellowiki/controllers/wikiparser/parser.py
fellowiki/controllers/wikiparser/special_characters.py
fellowiki/controllers/wikiparser/special_markup.py
fellowiki/controllers/wikiparser/structure_modifiers.py
fellowiki/controllers/wikiparser/tables.py
fellowiki/controllers/wikiparser/text_style.py
fellowiki/controllers/wikiparser/text_style_simple.py
fellowiki/controllers/wikiparser/util.py
fellowiki/controllers/wikiparser/tests/__init__.py
fellowiki/controllers/wikiparser/tests/test_parser.py
fellowiki/controllers/wikiparser/tests/tests/mixed_markup/bold_concurrent.complete.xml
fellowiki/controllers/wikiparser/tests/tests/mixed_markup/bold_concurrent.extension_escaped_text.xml
fellowiki/controllers/wikiparser/tests/tests/mixed_markup/bold_concurrent.extension_headlines.xml
fellowiki/controllers/wikiparser/tests/tests/mixed_markup/bold_concurrent.extension_links.xml
fellowiki/controllers/wikiparser/tests/tests/mixed_markup/bold_concurrent.extension_lists.xml
fellowiki/controllers/wikiparser/tests/tests/mixed_markup/bold_concurrent.extension_macros.xml
fellowiki/controllers/wikiparser/tests/tests/mixed_markup/bold_concurrent.extension_special_characters.xml
fellowiki/controllers/wikiparser/tests/tests/mixed_markup/bold_concurrent.extension_special_markup.xml
fellowiki/controllers/wikiparser/tests/tests/mixed_markup/bold_concurrent.extension_structure_modifiers.xml
fellowiki/controllers/wikiparser/tests/tests/mixed_markup/bold_concurrent.extension_tables.xml
