Metadata-Version: 1.0
Name: FelloWiki
Version: 0.01a1.dev-r36
Summary: Yet another wiki engine
Home-page: http://developer.berlios.de/projects/fellowiki/
Author: Jan Niklas Fingerle
Author-email: fingerle@users.berlios.de
License: MIT-style
Download-URL: http://developer.berlios.de/project/showfiles.php?group_id=6220
Keywords: turbogears.app
Platform: UNKNOWN
Classifier: Development Status :: 3 - Alpha
Classifier: Operating System :: OS Independent
Classifier: Programming Language :: Python
Classifier: Topic :: Software Development :: Libraries :: Python Modules
Classifier: Framework :: TurboGears
Classifier: Framework :: TurboGears :: Applications
